<?xml version="1.0" encoding="UTF-8"?>
<review id="959" item="2000 BMW 3 Series" rating="1">
	<title>
		<sentence id="1">
			Warning(1) to(2) BMW(3) purchasers(4) 
		</sentence>
	</title>
	<pros>
		<sentence id="1">
			Styling(1) ,(2) drive(3) of(4) the(5) vehicle(6) 
		</sentence>
	</pros>
	<cons>
		<sentence id="1">
			Rattles(1) ,(2) groans(3) ,(4) constant(5) trips(6) to(7) shop(8) 
		</sentence>
	</cons>
	<bottomLine>
		<sentence id="1">
			Do(1) not(2) buy(3) a(4) BMW(5) .(6) 
			<opinion polarity="-" feature="car" opWords="2,3"/>
		</sentence>
	</bottomLine>
	<text>
		<sentence id="1">
			You(1) will(2) not(3) believe(4) the(5) experience(6) that(7) I(8) have(9) had(10) with(11) BMW(12) .(13) 
		</sentence>
		<sentence id="2">
			This(1) car(2) has(3) been(4) in(5) the(6) shop(7) a(8) total(9) of(10) 38(11) days(12) since(13) I(14) leased(15) it(16) last_May(17) ((18) 2000(19) )(20) .(21) 
		</sentence>
		<sentence id="3">
			There(1) are(2) so(3) many(4) problems(5) with(6) these(7) cars(8) that(9) you(10) do(11) not(12) hear(13) about(14) .(15) 
		</sentence>
		<sentence id="4">
			BMW(1) has(2) had(3) to(4) replace(5) the(6) window(7) regulators(8) three_times(9) due(10) to(11) '(12) engineering(13) flaws(14) '(15) .(16) 
		</sentence>
		<sentence id="5">
			They(1) tell(2) me(3) the(4) window(5) regulators(6) are(7) very(8) common(9) problems(10) .(11) 
		</sentence>
		<sentence id="6">
			They(1) will(2) cause(3) your(4) window(5) to(6) not(7) roll(8) up(9) or(10) to(11) stop(12) midway(13) .(14) 
		</sentence>
		<sentence id="7">
			The(1) moonroof(2) at(3) times(4) will(5) decide(6) it(7) does(8) not(9) want(10) to(11) open(12) or(13) close(14) .(15) 
		</sentence>
		<sentence id="8">
			They(1) have(2) replaced(3) the(4) moonroof(5) motor(6) twice(7) .(8) 
		</sentence>
		<sentence id="9">
			The(1) car(2) only(3) has(4) 18,000_miles(5) on(6) it(7) and(8) it(9) is(10) in(11) the(12) shop(13) every(14) other(15) month(16) .(17) 
		</sentence>
		<sentence id="10">
			This(1) month(2) ,(3) the(4) A(5) /(6) C(7) blower(8) decided(9) to(10) stop(11) working(12) ,(13) and(14) I(15) was(16) told(17) that(18) was(19) a(20) common(21) problem(22) too(23) .(24) 
		</sentence>
		<sentence id="11">
			The(1) CD(2) player(3) will(4) not(5) eject(6) at(7) times(8) .(9) 
		</sentence>
		<sentence id="12">
			The(1) two(2) main(3) problems(4) I(5) am(6) having(7) are(8) a(9) loud(10) rattling(11) noise(12) that(13) comes(14) from(15) the(16) exterior(17) driver(18) door(19) when(20) the(21) car(22) is(23) wet(24) at(25) 70(26) mph(27) and(28) the(29) door(30) rattle(31) that(32) happens(33) when(34) you(35) go(36) over(37) bumps(38) .(39) 
		</sentence>
		<sentence id="13">
			Everyone(1) at(2) BMW(3) claims(4) that(5) these(6) are(7) common(8) occurrences(9) with(10) all(11) 2000(12) 3-series(13) ,(14) so(15) if(16) anyone(17) else(18) out(19) there(20) has(21) a(22) 4(23) door(24) 3-series(25) ,(26) tell(27) me(28) if(29) you(30) have(31) these(32) problems(33) too(34) ...(35) Here(36) 's(37) the(38) real(39) catch(40) .(41) 
		</sentence>
		<sentence id="14">
			I(1) have(2) been(3) so(4) frustrated(5) that(6) I(7) went(8) to(9) BMW_North_America(10) .(11) 
			<opinion polarity="-" feature="car" opWords="5" potency="4"/>
		</sentence>
		<sentence id="15">
			The(1) Local_Market_Manager(2) that(3) I(4) have(5) been(6) dealing(7) never(8) returned(9) any(10) of(11) my(12) phone(13) calls(14) .(15) 
		</sentence>
		<sentence id="16">
			Since(1) I(2) did(3) not(4) get(5) any(6) response(7) from(8) him(9) ,(10) I(11) contacted(12) another(13) BMW_NA(14) customer(15) service(16) rep(17) who(18) told(19) me(20) to(21) write(22) him(23) a(24) letter(25) containing(26) all(27) my(28) problems(29) .(30) 
		</sentence>
		<sentence id="17">
			What(1) did(2) he(3) do(4) ?(5) 
		</sentence>
		<sentence id="18">
			Sent(1) the(2) letter(3) to(4) guy(5) who(6) would(7) not(8) return(9) my(10) phone(11) calls(12) !(13) !(14) 
		</sentence>
		<sentence id="19">
			His(1) response(2) :(3) If(4) you(5) 're(6) that(7) unhappy(8) ,(9) sue(10) us(11) .(12) 
			<opinion polarity="-" feature="car" opWords="8"/>
		</sentence>
		<sentence id="20">
			I(1) have(2) filed(3) the(4) Lemon_Law(5) and(6) am(7) waiting(8) arbitration(9) now(10) .(11) 
		</sentence>
		<sentence id="21">
			The(1) service(2) manager(3) at(4) the(5) dealership(6) has(7) no(8) response(9) for(10) me(11) .(12) 
		</sentence>
		<sentence id="22">
			No(1) one(2) has(3) any(4) resolve(5) for(6) the(7) issue(8) .(9) 
		</sentence>
		<sentence id="23">
			The(1) car(2) still(3) rattles(4) and(5) groans(6) ,(7) and(8) no(9) one(10) at(11) BMW(12) seems(13) to(14) want(15) to(16) help(17) .(18) 
			<opinion polarity="-" feature="car" featWords="2" opWords="6"/>
			<opinion polarity="-" feature="car" featWords="2" opWords="4"/>
		</sentence>
		<sentence id="24">
			So(1) much(2) for(3) their(4) dedication(5) to(6) customer(7) satisfaction(8) .(9) 
		</sentence>
		<sentence id="25">
			UPDATE(1) 12.27.01(2) --(3) BMW(4) has(5) just(6) terminated(7) my(8) lease(9) and(10) is(11) going(12) to(13) pay(14) the(15) termination(16) fee(17) .(18) 
		</sentence>
		<sentence id="26">
			I(1) have(2) just(3) gotten(4) rid(5) of(6) my(7) first(8) and(9) last(10) BMW(11) .(12) 
		</sentence>
		<sentence id="27">
			This(1) is(2) about(3) the(4) only(5) good(6) thing(7) that(8) BMW(9) has(10) done(11) !(12) 
		</sentence>
		<sentence id="28">
			Amount_Paid(1) ((2) US(3) $(4) )(5) :(6) 37000(7) Condition(8) :(9) NewModel_Year(10) :(11) 2000(12) 
		</sentence>
	</text>
</review>
